ua_gec/__init__.py
ua_gec/annotated_text.py
ua_gec/corpus.py
ua_gec/stats.py
ua_gec-2.1.0.dist-info/METADATA
ua_gec-2.1.0.dist-info/WHEEL
ua_gec-2.1.0.dist-info/top_level.txt
ua_gec-2.1.0.dist-info/RECORD
