Metadata-Version: 2.1
Name: ua-gec
Version: 2.1.0
Summary: UA-GEC: Grammatical Error Correction and Fluency Corpus for the Ukrainian language
Home-page: https://github.com/grammarly/ua-gec
Author: Oleksiy Syvokon
Author-email: oleksiy.syvokon@gmail.com
License: License :: OSI Approved :: CC-BY-4.0
Keywords: gec ukrainian dataset corpus grammatical error correction grammarly
Classifier: Development Status :: 3 - Alpha
Classifier: Intended Audience :: Developers
Classifier: Intended Audience :: Education
Classifier: Intended Audience :: Science/Research
Classifier: Natural Language :: Ukrainian
Classifier: License :: CC0 1.0 Universal (CC0 1.0) Public Domain Dedication
Classifier: Programming Language :: Python :: 3
Classifier: Programming Language :: Python :: 3.6
Classifier: Programming Language :: Python :: 3.7
Classifier: Programming Language :: Python :: 3.8
Classifier: Programming Language :: Python :: 3.9
Classifier: Programming Language :: Python :: 3.10
Classifier: Programming Language :: Python :: 3.11
Requires-Python: >=3.6
Provides-Extra: test
Requires-Dist: pytest ; extra == 'test'
Requires-Dist: coverage ; extra == 'test'
